agora_twin_property/__init__.py
agora_twin_property/twin_property.py
agora_twin_property/twin_property_observer.py
agora_twin_property/version.py
agora_twin_property-3.0.2.dist-info/licenses/LICENSE
agora_twin_property-3.0.2.dist-info/WHEEL
agora_twin_property-3.0.2.dist-info/METADATA
agora_twin_property-3.0.2.dist-info/RECORD
