Metadata-Version: 2.4
Name: agora_twin_property
Version: 3.0.2
Summary: Agora twin property for the Agora Edge Apps SDK 2.0 (Python)
Author-email: AgoraIoT <agoraiot@slb.com>
Classifier: License :: OSI Approved :: Apache Software License
License-File: LICENSE
Requires-Dist: agora_logging == 3.0.2
Requires-Dist: agora_config == 3.0.2
Requires-Dist: agora_redis_client == 3.0.2
Project-URL: Home, https://slb-edge.github.io
